{
  "units": {
    "Scum": {
      "Commander": [{
          "name": "Tyber Zann",
          "title": "Cold, Methodical, and Ruthless",
          "image": "http://cloud-3.steamusercontent.com/ugc/1638738505735070640/74612E44D0AF4F505937EE2E0DAF21C08EB4E15B/",
          "size": "small",
          "type": "Trooper",
          "points": 140,
          "speed": 2,
          "upgrades": {
            "Command": 1,
            "Training": 1,
            "Illicit": 1,
            "Gear": 1
          },
          "minis": [{
            "mesh": "http://cloud-3.steamusercontent.com/ugc/1021696642365775807/337D2A5009DD4A91F0A469B418D4C77867FDF52D/",
            "diffuse": "http://cloud-3.steamusercontent.com/ugc/1021696642365776115/8606DE28865E723D2343D17F890A99959E25AC8F/"
          }],
          "commands": [{
              "name": "Orbital Bombardment",
              "image": "http://cloud-3.steamusercontent.com/ugc/1638738505735071380/B7CEA3F14638418D63BEFF3F7A611F5078D31667/",
              "pip": 1
            },
            {
              "name": "Corruption is My Weapon",
              "image": "http://cloud-3.steamusercontent.com/ugc/1638738505735071871/7524B10AD4DB25DAA1E5F5F0275A58DE9C3EC666/",
              "pip": 2
            },
            {
              "name": "Everyone Has a Price",
              "image": "http://cloud-3.steamusercontent.com/ugc/1638738505735072378/3A407CC85B615E03763D5F22E7116CA3FB217F0B/",
              "pip": 3
            }
          ]
        },
        {
          "name": "Urai Fen",
          "title": "Loyal Lieutenant",
          "image": "http://cloud-3.steamusercontent.com/ugc/1638738505735039360/1B0C02842ADDAA687687E529BE8B33983CAD933F/",
          "size": "small",
          "type": "Trooper",
          "points": 90,
          "speed": 2,
          "upgrades": {
            "Training": 2,
            "Illicit": 1,
            "Gear": 1
          },
          "minis": [{
            "mesh": "http://cloud-3.steamusercontent.com/ugc/1021696984835649865/8FC3F2E4E22555D72BDF283AD0E686537F33A043/",
            "diffuse": "http://cloud-3.steamusercontent.com/ugc/1021696984835650100/057E08B03AAE7CA89B585D8916BB25023B63341A/"
          }],
          "commands": [{
              "name": "Strike and Fade",
              "image": "http://cloud-3.steamusercontent.com/ugc/1638738505735040340/32D15FA78098AB05AD6D98B51631935EC6DEC3C3/",
              "pip": 1
            },
            {
              "name": "The Consortium Commands It",
              "image": "http://cloud-3.steamusercontent.com/ugc/1638738505735041426/F309B5F10C9F44B3E9FE50A42FAD541185DEE9A5/",
              "pip": 2
            },
            {
              "name": "No Mission is too Dangerous",
              "image": "http://cloud-3.steamusercontent.com/ugc/1638738505735047596/1516182BE8ED3D0635F56F830C4FB85F869C477C/",
              "pip": 3
            }
          ]
        }
      ],
      "Operative": [{
        "name": "Silri",
        "title": "Dark Witch",
        "image": "http://cloud-3.steamusercontent.com/ugc/1638738505735151492/82278C71E894B0710E02376909241ECAAD41F8C7/",
        "size": "small",
        "type": "Trooper",
        "points": 150,
        "speed": 2,
        "upgrades": {
          "Force": 1,
          "Training": 2,
          "Illicit": 1
        },
        "minis": [{
          "mesh": "http://cloud-3.steamusercontent.com/ugc/1021696984835654759/B33E7C3B1D34E7DDAC7B617DC466F12FF66774E1/",
          "diffuse": "http://cloud-3.steamusercontent.com/ugc/1021696984835654931/3ACEDEC6F99A311A245C7492883DAB9720D05348/"
        }],
        "commands": [{
            "name": "I Shall Rip Out Their Souls",
            "image": "http://cloud-3.steamusercontent.com/ugc/1638738505735165967/E52C14F2A96A0DDA785B12C9400F47E9E5E2F4A7/",
            "pip": 1
          },
          {
            "name": "Come Closer",
            "image": "http://cloud-3.steamusercontent.com/ugc/1638738505735165400/6E97DF5AC3BF3172E316DD409240AA04BD4C6DE4/",
            "pip": 2
          },
          {
            "name": "They Will Know Fear",
            "image": "http://cloud-3.steamusercontent.com/ugc/1638738505735164916/B6CDD990B416AE4B7897AB3A27E35ACD4A46DE07/",
            "pip": 3
          }
        ]
      }],
      "Corps": [{
        "name": "Grenadier Squad",
        "image": "http://cloud-3.steamusercontent.com/ugc/1638738505735128053/8071373F43B26B004A85BB1423AE10D8BA9FA2D9/",
        "size": "small",
        "type": "Trooper",
        "points": 33,
        "speed": 2,
        "upgrades": {
          "Personnel": 1,
          "Illicit": 1,
          "Comms": 1,
          "Gear": 1,
          "Grenades": 2
        },
        "minis": [{
            "mesh": "http://cloud-3.steamusercontent.com/ugc/1021696642365822891/9245AC0020E31C369AE4129B35D0BA467A01F2B4/",
            "diffuse": "http://cloud-3.steamusercontent.com/ugc/1021696642365823446/E94BC334A0B2F95CFB75FEDC3A0FEDF2FFD5A970/"
          },
          {
            "mesh": "http://cloud-3.steamusercontent.com/ugc/1021696642365824294/5F43B720E0198A078E25BA472E7DDBCA8F51CBEC/",
            "diffuse": "http://cloud-3.steamusercontent.com/ugc/1021696642365824481/27693FC709ADF50440623C6347A11151608D5E2F/"
          },
          {
            "mesh": "http://cloud-3.steamusercontent.com/ugc/1021696642365824294/5F43B720E0198A078E25BA472E7DDBCA8F51CBEC/",
            "diffuse": "http://cloud-3.steamusercontent.com/ugc/1021696642365824481/27693FC709ADF50440623C6347A11151608D5E2F/"
          }
        ]
      }],
      "Special Forces": [{
        "name": "Mercenary Assault Squad",
        "image": "http://cloud-3.steamusercontent.com/ugc/1638738505735112958/CA567516B908134719A9891C1855E81C88E39E7E/",
        "size": "small",
        "type": "Trooper",
        "points": 72,
        "speed": 1,
        "upgrades": {
          "Heavy Weapon": 1,
          "Training": 1,
          "Illicit": 1,
          "Gear": 1,
          "Armament": 1
        },
        "minis": [{
            "mesh": "http://cloud-3.steamusercontent.com/ugc/1021696642365876771/3C9BD90A0E8E6BA277A1133D1AF61B2D44C2DEB0/",
            "diffuse": "http://cloud-3.steamusercontent.com/ugc/1021696642365877132/5DEAE7FFFF586E0ACBFD5BB29AF4869E6D675044/"
          },
          {
            "mesh": "http://cloud-3.steamusercontent.com/ugc/1021696642365880281/45B6B327A692DBFDE6D5E5F642EB7FEBBC2A0A4F/",
            "diffuse": "http://cloud-3.steamusercontent.com/ugc/1021696642365878394/8AD2A611C51D78184D8E4204A720C59EEC2C7755/"
          },
          {
            "mesh": "http://cloud-3.steamusercontent.com/ugc/1021696642365879761/026D7FD22C9074A12068AE05CE293EBB833FC70E/",
            "diffuse": "http://cloud-3.steamusercontent.com/ugc/1021696642365878394/8AD2A611C51D78184D8E4204A720C59EEC2C7755/"
          },
          {
            "mesh": "http://cloud-3.steamusercontent.com/ugc/1021696642365879295/EC66EBB1550D6D61DAC1AC96CAE92A0273B06A45/",
            "diffuse": "http://cloud-3.steamusercontent.com/ugc/1021696642365878394/8AD2A611C51D78184D8E4204A720C59EEC2C7755/"
          }
        ]
      }],
      "Heavy": [{
        "name": "Cuddles",
        "image": "http://cloud-3.steamusercontent.com/ugc/1638738493660718148/F2EBC8B208958A7DE241A7E6A2989B2EDEFA8A7F/",
        "size": "huge",
        "type": "Creature Trooper",
        "points": 135,
        "speed": 1,
        "upgrades": {
          "Creature": 1
        },
        "minis": [{
          "mesh": "http://cloud-3.steamusercontent.com/ugc/1021696984835661685/1668BEEE179A260B9988D3C60872160FF93CEE51/",
          "diffuse": "http://cloud-3.steamusercontent.com/ugc/1021696984835661821/7B52CEEC4169ACB4A32C0489D4A878BC72030DE2/"
        }]
      }]
    }
  },
  "upgrades": {
    "Armament": [{
      "name": "DXR-6 Focused Fire Config",
      "image": "http://cloud-3.steamusercontent.com/ugc/1638738505735115917/9E0BA5F8013B1491D5EF74BED3C484BA0F3052AB/",
      "flip": {
        "name": "DXR-6 Power Shot Config",
        "image": "http://cloud-3.steamusercontent.com/ugc/1638738505735116297/419AF3D6925D7004CA92BE249969A1BFB42B9742/"
      },
      "points": 8,
      "restrictions": {
        "include": {
          "unit": ["Mercenary Assault Squad"]
        }
      }
    }],
    "Command": [{
      "name": "Racketeering",
      "image": "http://cloud-3.steamusercontent.com/ugc/1638738505735072829/84C080C8B919D06884AF3BC12ADDB58B524C5271/",
      "points": 5,
      "restrictions": {
        "include": {
          "unit": ["Tyber Zann"]
        }
      }
    }],
    "Heavy Weapon": [{
        "name": "ACP Trooper",
        "image": "http://cloud-3.steamusercontent.com/ugc/1638738505735115264/1D92758AC20C28AA48019DCD564E31D271B20A2C/",
        "mini": {
          "mesh": "http://cloud-3.steamusercontent.com/ugc/1021698068156270983/519A43ACE1F5461D51AA1BA81ADF4A5C37BEF9E4/",
          "diffuse": "http://cloud-3.steamusercontent.com/ugc/1021698068156271135/318D90BCDE4E3E362797A38823A21FF17FAF651E/"
        },
        "points": 30,
        "restrictions": {
          "include": {
            "unit": ["Mercenary Assault Squad"]
          }
        }
      },
      {
        "name": "Concussion Rifle Trooper",
        "image": "http://cloud-3.steamusercontent.com/ugc/1638738505735114688/7F06A4AA27BBEFE8D08FF392CB8E7E8FC4083F6B/",
        "mini": {
          "mesh": "http://cloud-3.steamusercontent.com/ugc/1021698068156271785/233649FA9B56D451B97E71E706C777AD529B0810/",
          "diffuse": "http://cloud-3.steamusercontent.com/ugc/1021698068156271944/671F0E7483F7DA3D92D551E5042698EE06E510EB/"
        },
        "points": 30,
        "restrictions": {
          "include": {
            "unit": ["Mercenary Assault Squad"]
          }
        }
      },
      {
        "name": "Mercenary Assault Trooper",
        "image": "http://cloud-3.steamusercontent.com/ugc/1638738505735114176/44B42375B5C11B5BADA3029FC1BF45BBCE56575C/",
        "mini": {
          "mesh": "http://cloud-3.steamusercontent.com/ugc/1021696642365878231/A04BECDA5804E0A38FF974528C70AB5AAAE4B715/",
          "diffuse": "http://cloud-3.steamusercontent.com/ugc/1021696642365878394/8AD2A611C51D78184D8E4204A720C59EEC2C7755/"
        },
        "points": 18,
        "restrictions": {
          "include": {
            "unit": ["Mercenary Assault Squad"]
          }
        }
      }
    ],
    "Illicit": [{
        "name": "Glitterstim",
        "image": "http://cloud-3.steamusercontent.com/ugc/1638738416603891098/84A7F8CE1B7AEA3F5B65079E0EB56B1FB18E920C/",
        "points": 5,
        "restrictions": {
          "include": {
            "type": ["Trooper"]
          }
        }
      },
      {
        "name": "Black Market Weapon Modifications",
        "image": "http://cloud-3.steamusercontent.com/ugc/1638738416607468746/9BB47BF9A1EADE6F9FE3F2E6E5C6EE4F87ADFBF5/",
        "points": 10,
        "restrictions": {
          "include": {
            "type": ["Trooper"]
          }
        }
      },
      {
        "name": "Stimpack",
        "image": "http://cloud-3.steamusercontent.com/ugc/1638738505735182732/C3B2C7FA3F05FC71D5C3ED089A8037A92171A103/",
        "points": 5,
        "restrictions": {
          "include": {
            "type": ["Trooper"]
          }
        }
      },
      {
        "name": "Personal Shield",
        "image": "http://cloud-3.steamusercontent.com/ugc/1638738505735181899/208D960208099BDF4461E2E09204169FF959FC52/",
        "points": 8,
        "restrictions": {
          "include": {
            "type": ["Trooper"]
          }
        }
      },
      {
        "name": "Outer Rim Modifications",
        "image": "http://cloud-3.steamusercontent.com/ugc/1638738416607479220/9FD7DEA0460FAA03A3C6BBB410D029405FE6F57F/",
        "points": 10,
        "restrictions": {
          "include": {
            "type": ["Droid Trooper", "Ground Vehicle", "Repulsor Vehicle"]
          }
        }
      },
      {
        "name": "Self-Destruct Sequencing",
        "image": "http://cloud-3.steamusercontent.com/ugc/1638738416607481441/3D72AB420E13BC2083A6266950F8A581807B6D15/",
        "points": 5,
        "restrictions": {
          "include": {
            "type": ["Droid Trooper", "Ground Vehicle", "Repulsor Vehicle"]
          }
        }
      }
    ],
    "Personnel": [{
        "name": "Extra Grenadier",
        "image": "http://cloud-3.steamusercontent.com/ugc/1638738505735129141/9805A2223DB725582E8105414121E4505895193F/",
        "mini": {
          "mesh": "http://cloud-3.steamusercontent.com/ugc/1021696642365824294/5F43B720E0198A078E25BA472E7DDBCA8F51CBEC/",
          "diffuse": "http://cloud-3.steamusercontent.com/ugc/1021696642365824481/27693FC709ADF50440623C6347A11151608D5E2F/"
        },
        "points": 11,
        "restrictions": {
          "include": {
            "unit": ["Grenadier Squad"]
          }
        }
      },
      {
        "name": "Forward Observer",
        "image": "http://cloud-3.steamusercontent.com/ugc/1638738505735128538/8947A618AAA4A4A0D92B3C7C12E651A494FDEDA7/",
        "mini": {
          "mesh": "http://cloud-3.steamusercontent.com/ugc/1021696984835690936/3C42012D036A5F420DD9ADD158E66901AB4A5671/",
          "diffuse": "http://cloud-3.steamusercontent.com/ugc/1021696984835691208/1C0C86466F3298E9663CEE3961B7F3F6DBED4DD9/"
        },
        "points": 17,
        "restrictions": {
          "include": {
            "unit": ["Grenadier Squad"]
          }
        }
      }
    ],
    "Training": [{
        "name": "Blend In",
        "image": "http://cloud-3.steamusercontent.com/ugc/1638738505735182379/DD072454059CA2BB5CB206848D0BCBF656F494F9/",
        "points": 10,
        "restrictions": {
          "include": {
            "faction": ["Scum"],
            "rank": ["Commander", "Operative", "Special Forces"]
          }
        }
      },
      {
        "name": "Faithful Companion",
        "image": "http://cloud-3.steamusercontent.com/ugc/1638738505735164302/4C5E96A3397E6BD2F8C07A61AA9B25FDC0D8C031/",
        "points": 8,
        "restrictions": {
          "include": {
            "unit": ["Beast Master", "Silri"]
          }
        }
      }
    ]
  }
}
